Workbook

Sheet SUMMARY & COST DISTRIBUTION
A16: NESTURA DESIGNS (formerly SA INTERIOR SCAPES)
A17: SUMMARY
A18: Client Name | B18: Pratichi behera
A19: Requirement | B19: 2 BHK
A20: Property Type | B20: Flat
A21: Property Age | B21: New
A22: Location | B22: VTP Sierra, Sus
A23: Quotation by | B23: Aishwarya Khinvasara
A24: Date | B24: =TODAY() -> 9/11/2026
A28: Project Cost Distrubution
A30: [A] Furniture Works Costs
A61: Area/Room | B61: Cost
A62: ='DETAILED ESTIMATE'!B4 -> ENTRANCE FOYER AREA | B62: ='DETAILED ESTIMATE'!J13 -> ₹ 40,200
A63: ='DETAILED ESTIMATE'!B15 -> LIVING AREA | B63: ='DETAILED ESTIMATE'!J26 -> ₹ 121,200
A64: ='DETAILED ESTIMATE'!B28 -> BALCONY | B64: ='DETAILED ESTIMATE'!J34 -> ₹ 40,500
A65: ='DETAILED ESTIMATE'!B36 -> KITCHEN | B65: ='DETAILED ESTIMATE'!J49 -> ₹ 486,800
A66: ='DETAILED ESTIMATE'!B51 -> FIRST GUEST BEDROOM | B66: ='DETAILED ESTIMATE'!J68 -> ₹ 167,500
A67: ='DETAILED ESTIMATE'!B70 -> SECOND KIDS BEDROOM | B67: ='DETAILED ESTIMATE'!J83 -> ₹ 178,380
A68: ='DETAILED ESTIMATE'!B85 -> BATHROOM (COMMON ROOM) | B68: ='DETAILED ESTIMATE'!J92 -> ₹ 0
A69: ='DETAILED ESTIMATE'!B94 -> THIRD MASTER BEDROOM | B69: ='DETAILED ESTIMATE'!J105 -> ₹ 272,440
A70: * Actual cost of all items above may change as per actuals
A71: Furniture Works Total | B71: =SUM(B62:B70) -> ₹ 1,307,020
A74: [B] Other Works Cost
A103: Item | B103: Cost
A104: ='DETAILED ESTIMATE'!B109 -> FALSE CEILING WORK | B104: ='DETAILED ESTIMATE'!J126 -> ₹ 77,378
A105: ='DETAILED ESTIMATE'!B128 -> PAINTING & WALL FINISHES | B105: ='DETAILED ESTIMATE'!J144 -> ₹ 122,000
A106: ='DETAILED ESTIMATE'!B146 -> ELECTRICAL WORK | B106: ='DETAILED ESTIMATE'!J159 -> ₹ 92,900
A107: ='DETAILED ESTIMATE'!B161 -> AIR- CONDITIONING WORK | B107: ='DETAILED ESTIMATE'!J166 -> ₹ 0
A108: ='DETAILED ESTIMATE'!B168 -> PLUMBING WORK | B108: ='DETAILED ESTIMATE'!J174 -> ₹ 35,000
A109: ='DETAILED ESTIMATE'!B176 -> CIVIL WORK | B109: ='DETAILED ESTIMATE'!J189 -> ₹ 74,800
A110: ='DETAILED ESTIMATE'!B191 -> FABRICATION WORK | B110: ='DETAILED ESTIMATE'!J201 -> ₹ 0
A111: ='DETAILED ESTIMATE'!B203 -> FABRICS AND STICHING | B111: ='DETAILED ESTIMATE'!J217 -> ₹ 90,900
A112: ='DETAILED ESTIMATE'!B219 -> BOUGHT OUT ITEMS (subject to selection) | B112: ='DETAILED ESTIMATE'!J232 -> ₹ 227,000
A113: ='DETAILED ESTIMATE'!B234 -> MISCELLANEOUS ITEMS (subject to selection) | B113: ='DETAILED ESTIMATE'!J246 -> ₹ 8,000
A114: * Actual cost of all items above may change as per actuals
A115: Other Works Total | B115: =SUM(B104:B113) -> ₹ 727,978
A117: Total Project Cost
A118: [A] Furnitue Works Total | B118: =B71 -> ₹ 1,307,020
A119: [B] Other Works Total | B119: =B115 -> ₹ 727,978
A120: [C] Project Cost (A + B) | B120: =B118+B119 -> ₹ 2,034,998
A121: [D] Contingencies (5% of Project Cost) | B121: =5%*B120 -> ₹ 101,750
A122: [E] Total Project Cost (C + D) | B122: =B121+B120 -> ₹ 2,136,748
A123: Interior Design Fees
A124: LUMPSUM | B124: ='INTERIOR FEES'!C9
A125: [G] Interior Design Fees | B125: ='INTERIOR FEES'!E23 -> ₹ 225,000
A126: Final Project Cost
A127: TOTAL PROJECT COST + INTERIOR DESIGN FEES (E+G) | B127: =B122+B125 -> ₹ 2,361,748

Sheet DETAILED ESTIMATE
A1: NESTURA DESIGNS (formerly SA INTERIOR SCAPES)
A2: DETAILED ESTIMATE
A3: S.NO | B3: ITEM | C3: PROPOSED DETAILS/MATERIALS | D3: LENGTH | E3: BREADTH | F3: NO.S | G3: QUANTITY (APPROX) | H3: UNITS | I3: RATE | J3: GRAND TOTAL
A4: A | B4: ENTRANCE FOYER AREA
A6: 1 | B6: SAFTEY DOOR | C6: a)Safety Door with Metal Grill and Godgrej Lock | D6: 7.5 | E6: 3 | F6: 1 | G6: =F6*E6*D6 -> 22.5 | H6: sq.ft | I6: 1850 | J6: NA
A7: 2 | B7: MAIN DOOR | C7: a) flush door saftey door.(Finish - Matt finish ) (Open style - Hinged/Swing/Sliding) handles and b)locks cost subject to selection as per desgin | D7: 7.3 | E7: 3.6 | F7: 1 | G7: =F7*E7*D7 -> 26.28 | H7: sq.ft | I7: 1800 | J7: NA
A8: 3 | B8: ENTRANCE DESIGNER PANEL | C8: a) name plate with paneling of plywood | D8: 7 | E8: 9 | F8: 1 | G8: 72 | H8: sq.ft | I8: 800 | J8: NA
A9: 4 | B9: SHOE RACK | C9: a) plywood shoe rack with laminate finish. | D9: 4 | E9: 4 | F9: 1 | G9: =F9*E9*D9 -> 16 | H9: sq.ft | I9: 2200 | J9: =I9*G9 -> ₹ 35,200.00
A10: 6 | B10: NAME PLATE | C10: a) name plate with paneling of plywood | D10: 2 | E10: 2 | F10: 1 | G10: =F10*E10*D10 -> 4 | H10: sq.ft | I10: LUMPSUM | J10: 5000
A11: 6 | B11: FOYER WALL WITH PANELING | C11: paneling of plywood | D11: 4.5 | E11: 6 | F11: 1 | G11: =F11*E11*D11 -> 27 | H11: sq.ft | I11: 800 | J11: NA
A13: TOTAL OF ENTRANCE FOYER AREA | J13: =SUM(J6:J10) -> ₹ 40,200.00
A15: B | B15: LIVING AREA
A16: 1 | B16: TV UNIT DESIGNER PANELLING | C16: Left Size Wall Panel with shelves a) Providing & making of 2" thk paneling.Framework and 8mm thk . ply treated with LAMINATE AND WALL PAPER | D16: 5 | E16: 9 | F16: 1 | G16: =F16*E16*D16 -> 45 | H16: sq.ft | I16: 1000 | J16: =I16*G16 -> ₹ 45,000.00
A17: 2 | B17: BOOK SHELF | C17: b) 18mm plywood With Dark Walnut laminate with 2 drawers | D17: 7 | E17: 5 | F17: 1 | G17: =F17*E17*D17 -> 35 | H17: sq.ft | I17: 1800 | J17: NA
A18: 3 | B18: TV UNIT LEDGE | C18: b) 18mm plywood With Dark Walnut laminate with 2 drawers | D18: 5 | E18: 1.8 | F18: 1 | G18: =F18*E18*D18 -> 9 | H18: sq.ft | I18: 1800 | J18: =I18*G18 -> ₹ 16,200.00
A19: 4 | B19: DINING TABLE | C19: a) Material - plywood | D19: 6 | E19: 4 | F19: 1 | G19: =F19*E19*D19 -> 24 | H19: sq.ft | I19: 1800 | J19: =I19*G19 -> ₹ 43,200.00
A20: 5 | B20: DESIGNER PANELLING | C20: Sofa Back Wall Panelling with Wall Light | D20: 4 | E20: 9 | F20: 1 | G20: =F20*E20*D20 -> 36 | H20: sq.ft | I20: 900 | J20: NA
A21: 5 | B21: DESIGNER PANELLING | C21: Sofa Back Wall - Moulding integrated in pop | D21: 3 | E21: 7 | F21: 1 | G21: =F21*E21*D21 -> 21 | H21: sq.ft | I21: 800 | J21: =I21*G21 -> ₹ 16,800.00
A22: 6 | B22: AC PANELLING | C22: a) Providing designer wall | D22: 2 | E22: 18.6 | F22: 1 | G22: =F22*E22*D22 -> 37.2 | H22: sq.ft | I22: 900 | J22: NA
A23: 7 | B23: STORAGE ON DININNG WAL | C23: b) 18mm plywood With Dark Walnut laminate with 2 drawers and profile glass shutters | D23: 2 | E23: 5 | F23: 1 | G23: =F23*E23*D23 -> 10 | H23: sq.ft | I23: 1800 | J23: NA
A24: 8 | B24: MANDIR | C24: a) Providing and making a fluted glass mandir unit - Ihs with thin profile aluminum sections in black powder coated inside treated with 1 mm thk app shade of laminate with 4 nos of drawers & 1 nos. of 12 mm thk clear white glass shelf (basic cost of laminate upto Rs. 1500/- sheet) | D24: 3 | E24: 4 | F24: 1 | G24: =F24*E24*D24 -> 12 | H24: sq.ft | I24: 2100 | J24: =I24*G24 -> ₹ 25,200.00
A26: TOTAL OF LIVING AREA | J26: =SUM(J16:J23) -> ₹ 121,200.00
A28: C | B28: BALCONY
A29: 1 | B29: DESIGNER PANELLING | C29: Designer dado tiles with fitting | D29: 5 | E29: 9 | F29: 1 | G29: =F29*E29*D29 -> 45 | H29: sq.ft | I29: 900 | J29: =I29*G29 -> ₹ 40,500.00
A30: 2 | B30: SEATING/SWING | C30: a)granite top b) 18mm plywood With Dark Walnut laminate | D30: 2 | E30: 5 | F30: 1 | G30: =F30*E30*D30 -> 10 | H30: sq.ft | I30: 2100 | J30: NA
A31: 3 | B31: JANITER STORAGE | C31: b) 18mm plywood With Dark Walnut laminate | D31: 1 | E31: 7 | F31: 1 | G31: =F31*E31*D31 -> 7 | H31: sq.ft | I31: 1800 | J31: NA
A32: 4 | B32: OUTDOOR CHAIR AND COFFEE TABLE SET | C32: 2 Chairs and table | G32: 1 | H32: sq.ft | I32: 15000 | J32: NA
A34: TOTAL OF BALCONY AREA | J34: =SUM(J29:J32) -> ₹ 40,500.00
A36: D | B36: KITCHEN
A38: 1 | B38: KITCHEN TANDOMS | C38: a) Pre-laminated HDHMR/ BWP plywood withACRELIC lamination b)tandem hardware of EBCO BRAND 10TANDOMS | D38: 12 | E38: 3 | F38: 1 | G38: =F38*E38*D38 -> 36 | H38: sq.ft | I38: 6000 | J38: =I38*G38 -> ₹ 216,000.00
A39: 1 | B39: KITCHEN SHUTTERS | C39: a) Pre-laminated HDHMR/ BWP plywood with lamination b)tandem hardware of ebco brand | D39: 6 | E39: 3 | F39: 1 | G39: =F39*E39*D39 -> 18 | H39: sq.ft | I39: 3500 | J39: =I39*G39 -> ₹ 63,000.00
A40: 2 | B40: Over Counter Around Chimney ( Profile Doors + Acryilic laminate | C40: a) Providing and making a over head Storage made out of 19mm thk .Ply & finished in 1 mm thk approved laminate from both sides with ss rack onths.(basic cost of laminate upto Rs. 1500sheet.)(With necessary hardware like hinges, handles,lock,etc) as pes design | D40: 18 | E40: 2 | F40: 1 | G40: =F40*E40*D40 -> 36 | H40: sq.ft | I40: 2100 | J40: =I40*G40 -> ₹ 75,600.00
A41: 3 | B41: LOFT STORAGE | C41: a) Providing and making a over head Storage made out of 19mm thk .Ply & finished in 1 mm thk approved laminate (basic cost of laminate upto Rs. 1500sheet.)(With necessary hardware like hinges, handles,lock,etc) as pes design | D41: 18 | E41: 2 | F41: 1 | G41: =F41*E41*D41 -> 36 | H41: sq.ft | I41: 1800 | J41: =I41*G41 -> ₹ 64,800.00
A42: 4 | B42: APPLIANCESTORAGE /ROLLING SHUTTER | C42: a) HDHMR / bwp with laminate .Providing and making a Full ht Storage made out of 19mm thk .Ply & finished in 1 mm thk approved laminate from both sides.(basic cost of laminate upto Rs. 1500/-sheet.)(With necessary hardware like hinges handles.lock etc) | D42: 2 | E42: 5 | F42: 1 | G42: =F42*E42*D42 -> 10 | H42: sq.ft | I42: 3500 | J42: =I42*G42 -> ₹ 35,000.00
A43: 5 | B43: BREAKFAST COUNTER | C43: a) HDHMR / bwp with laminate .Providing and making a Full ht Storage made out of 19mm thk .Ply & finished in 1 mm thk approved laminate from both sides.(basic cost of laminate upto Rs. 1500/-sheet.)(With necessary hardware like hinges handles.lock etc) | D43: 4 | E43: 4 | F43: 1 | G43: =F43*E43*D43 -> 16 | H43: sq.ft | I43: 2200 | J43: NA
A44: 5 | B44: KITCHEN PANTRY | C44: a) HDHMR / bwp with laminate .Providing and making a Full ht Storage made out of 19mm thk .Ply & finished in 1 mm thk approved laminate from both sides.(basic cost of laminate upto Rs. 1500/-sheet.)(With necessary hardware like hinges handles.lock etc) | D44: 1.5 | E44: 7 | F44: 1 | G44: =F44*E44*D44 -> 10.5 | H44: sq.ft | I44: 4500 | J44: NA
A45: 6 | B45: DRY BALCONY STORAGE | C45: a) WPC dry balcony storage | D45: 3 | E45: 3 | F45: 2 | G45: =F45*E45*D45 -> 18 | H45: sq.ft | I45: 1800 | J45: =I45*G45 -> ₹ 32,400.00
A46: 7 | B46: SLIDING DOOR | C46: a) Providing & making kitchen sliding door made of 19 mm thk ply treated with 4mm thk app, laminate with 6 mm clear fluted glass on sliding track channel (lamp co.) with necessary door lock, handle etc. | D46: 7 | E46: 4 | F46: 1 | G46: =F46*E46*D46 -> 28 | H46: sq.ft | I46: 1800 | J46: NA
A47: 8 | B47: PARTITION | C47: a) Providing & making of kitchen 6" thk partition with 2" thk slit inside to hide out the door. made of necessary alum. Frame work and 9mm thk . ply finished in app shade of paint | D47: 7 | E47: 3 | F47: 1 | G47: =F47*E47*D47 -> 21 | H47: sq.ft | I47: 1300 | J47: NA
A49: TOTAL OF KITCHEN AREA | J49: =SUM(J38:J47) -> ₹ 486,800.00
A51: E | B51: FIRST GUEST BEDROOM
A53: 1 | B53: BED | C53: "18mm plywood bed with hydraulic storage, elegantly finished in laminate. | D53: 5 | E53: 6 | F53: 1 | G53: =F53*E53*D53 -> 30 | H53: sq.ft | I53: 1450 | J53: =G53*I53 -> ₹ 43,500.00
A54: 2 | B54: BED(CUSIONED BEDBACK) | C54: a) KDAP Headboard cusion backrest | D54: 3 | E54: 6 | F54: 1 | G54: =F54*E54*D54 -> 18 | H54: sq.ft | I54: 800 | J54: =G54*I54 -> ₹ 14,400.00
A55: 2 | B55: BEDBACK WALL PANEL | C55: Bed Back Wall Paneling | D55: 11 | E55: 7 | F55: 1 | G55: =F55*E55*D55 -> 77 | H55: sq.ft | I55: 700 | J55: NA
A56: 3 | B56: WARDROBE | C56: a) Providing & making of wardrobe with cane shutter in 19mm the .Ply 75 mm thk shutter frame to be treated with approved mm thk HDHMR finished in app shade of pu & white laminate from inside. (basic cost of laminate upto 1500 - sheet). With all necessary hardware like lock.handle hinge.etc. &(cost will vary as per design) | D56: 6 | E56: 9.5 | F56: 1 | G56: =F56*E56*D56 -> 57 | H56: sq.ft | I56: 1800 | J56: =G56*I56 -> ₹ 102,600.00
A57: 4 | B57: SIDE TABLE (WITH DRAWERS) | C57: a) Table of . plywood | D57: 1 | E57: 1.6 | F57: 2 | G57: 2 | H57: no.s | I57: 3500 | J57: =G57*I57 -> ₹ 7,000.00
A58: 4 | B58: STUDY TABLE WITH ONLY 2 DRAWERS | C58: a) Table with . plywood | D58: 5 | E58: 2.6 | F58: 1 | G58: =F58*E58*D58 -> 13 | H58: sq.ft | I58: 1800 | J58: NA
A59: 5 | B59: BOOK SHELF | C59: b) 18mm plywood With Dark Walnut laminate with 2 drawers | D59: 4 | E59: 4 | F59: 1 | G59: =F59*E59*D59 -> 16 | H59: sq.ft | I59: 1800 | J59: NA
A60: 6 | B60: WALLPAPER/TEXTURE PAINT | C60: Bought out item | D60: 8 | E60: 5 | F60: 1 | G60: =F60*E60*D60 -> 40 | H60: sq.ft | I60: 200 | J60: NA
A61: 7 | B61: WINDOW SEATING | C61: b) 18mm plywood With Dark Walnut laminate with 2 drawers | D61: 7 | E61: 3 | F61: 1 | G61: =F61*E61*D61 -> 21 | H61: sq.ft | I61: 1800 | J61: NA
A62: 8 | B62: T.V UNIT | C62: a) Providing and making a TV unit made out of 19mm thk .Ply treated with approved laminate from outside finished in approved shade of color lamination & white laminate from inside | D62: 6 | E62: 9 | F62: 1 | G62: =F62*E62*D62 -> 54 | H62: sq.ft | I62: 900 | J62: NA
A63: 9 | B63: DRESSING TABLE WITH MIROR STORAGE | C63: b) Exotic Teak Finish made of premium . plywood | D63: 4.6 | E63: 2 | F63: 1 | G63: =F63*E63*D63 -> 9.2 | H63: sq.ft | I63: 1800 | J63: NA
A64: 10 | B64: BEDROOM DOOR | C64: a) Providing & making door made of 19 mm thk ply treated with 4mm thk app, with necessary door lock, handle etc. | D64: 7 | E64: 3 | F64: 1 | G64: =F64*E64*D64 -> 21 | H64: sq.ft | I64: 800 | J64: NA
A65: 11 | B65: DOOR FRAME | C65: a) Providing & Making of bedroom door frame with 19mm thk .ply. b) Finished with approved laminate (cost will vary as per design) basic cost of laminate upto Rs.2000/sheet.) | D65: 7 | E65: 3 | F65: 1 | G65: =F65*E65*D65 -> 21 | H65: sq.ft | I65: 600 | J65: NA
A66: 12 | B66: AC PANELLING | C66: b) Providing & making of 2" thk panelling- - made of necessary alum.Frame work and 9mm thk . ply treated with laser cutted fluting HDHMR panel as per design detail finished in app shade. | D66: 2 | E66: 10.3 | F66: 1 | G66: =F66*E66*D66 -> 20.6 | H66: sq.ft | I66: 800 | J66: NA
A68: TOTAL OF FIRST BEDROOM | J68: =SUM(J52:J66) -> ₹ 167,500.00
A70: F | B70: SECOND KIDS BEDROOM
A72: 1 | B72: BED | C72: "18mm plywood bed with hydraulic storage, elegantly finished in laminate. | D72: 5 | E72: 6 | F72: 1 | G72: =F72*E72*D72 -> 30 | H72: sq.ft | I72: 1450 | J72: =G72*I72 -> ₹ 43,500.00
A73: 2 | B73: BED(CUSIONED BEDBACK) | C73: a) KDAP Headboard cusion backrest | D73: 3 | E73: 6 | F73: 1 | G73: =F73*E73*D73 -> 18 | H73: sq.ft | I73: 800 | J73: =G73*I73 -> ₹ 14,400.00
A74: 3 | B74: BEDBACK WALL PANEL | C74: Bed Back Wall Paneling | D74: 11 | E74: 7 | F74: 1 | G74: =F74*E74*D74 -> 77 | H74: sq.ft | I74: 700 | J74: NA
A75: 4 | B75: WARDROBE | C75: a) Providing & making of wardrobe with cane shutter in 19mm the .Ply 75 mm thk shutter frame to be treated with approved mm thk HDHMR finished in app shade of pu & white laminate from inside. (basic cost of laminate upto 1500 - sheet). With all necessary hardware like lock.handle hinge.etc. &(cost will vary as per design) | D75: 6 | E75: 9.5 | F75: 1 | G75: =F75*E75*D75 -> 57 | H75: sq.ft | I75: 1800 | J75: =G75*I75 -> ₹ 102,600.00
A76: 5 | B76: SIDE TABLE (WITH DRAWERS) | C76: a) Table of . plywood | D76: 1 | E76: 1.6 | F76: 2 | G76: 2 | H76: no.s | I76: 3500 | J76: =G76*I76 -> ₹ 7,000.00
A77: 6 | B77: STUDY TABLE WITH ONLY 2 DRAWERS | C77: a) Table with . plywood | D77: 2 | E77: 2.6 | F77: 1 | G77: =F77*E77*D77 -> 5.2 | H77: sq.ft | I77: 1400 | J77: =G77*I77 -> ₹ 7,280.00
A78: 7 | B78: DRESSING TABLE WITH MIROR STORAGE | C78: b) Exotic Teak Finish made of premium . plywood | D78: 9 | E78: 3 | F78: 1 | G78: =F78*E78*D78 -> 27 | H78: sq.ft | I78: 1200 | J78: NA
A79: 8 | B79: WHITE BOARD | C79: Back painted glass | D79: 2 | E79: 6 | F79: 1 | G79: =F79*E79*D79 -> 12 | H79: sq.ft | I79: 300 | J79: =G79*I79 -> ₹ 3,600.00
A80: 9 | B80: FOLDABLE TABLE | C80: a) Table with . plywood | D80: 2 | E80: 3 | F80: 1 | G80: =F80*E80*D80 -> 6 | H80: sq.ft | I80: 1800 | J80: NA
A83: TOTAL OF SECOND BEDROOM | J83: =SUM(J70:J80) -> ₹ 178,380.00
A85: G | B85: BATHROOM (COMMON ROOM)
A87: 1 | B87: BATHROOM FLUSH DOOR | C87: a) Providing & making bathroom door of 35mm th ..flush door finished with approved laminate from both sides with necessary hardware like hinges.handles, lock, etc) (basic cost of laminate upto Rs.2000/- sheet) | D87: 7 | E87: 3 | F87: 1 | G87: =F87*E87*D87 -> 21 | H87: sq.ft | I87: 900 | J87: NA
A88: 2 | B88: BATHROOM FLUSH DOOR FRAME | C88: a) Providing & Making of bathroom door frame with | 19mm thk .ply. Finished with approved laminate (cost will vary as per design basic cost of laminate upto Rs.2000 sheet.)2) | D88: 7 | E88: 3 | F88: 1 | G88: =F88*E88*D88 -> 21 | H88: sq.ft | I88: 500 | J88: NA
A89: 3 | B89: BELOW BASIN COUNTER STORAGE | C89: Installing Below-basin counter storage crafted from durable 18mm WPC board on both sides." | D89: 2 | E89: 2 | F89: 3 | G89: =F89*E89*D89 -> 12 | H89: sq.ft | I89: 1800 | J89: NA
A90: 3 | B90: ABOVE WC COUNTER STORAGE | C90: Installing Below-basin counter storage crafted from durable 18mm WPC board on both sides." | D90: 3 | E90: 4 | F90: 1 | G90: =F90*E90*D90 -> 12 | H90: sq.ft | I90: 1800 | J90: NA
A92: TOTAL OF BATHROOM | J92: =SUM(J87:J90) -> ₹ 0.00
A94: H | B94: THIRD MASTER BEDROOM
A96: 1 | B96: BED | C96: "18mm plywood bed with hydraulic storage, elegantly finished in laminate. | D96: 6 | E96: 5.6 | F96: 1 | G96: =F96*E96*D96 -> 33.6 | H96: sq.ft | I96: 1450 | J96: =G96*I96 -> ₹ 48,720.00
A97: 2 | B97: BED(CUSIONED BEDBACK) | C97: a) KDAP Headboard cusion backrest | D97: 3 | E97: 12 | F97: 1 | G97: =F97*E97*D97 -> 36 | H97: sq.ft | I97: 900 | J97: =G97*I97 -> ₹ 32,400.00
A98: 3 | B98: BEDBACK WALL PANEL | C98: Bed Back Wall Paneling | D98: 6 | E98: 12 | F98: 1 | G98: =F98*E98*D98 -> 72 | H98: sq.ft | I98: 800 | J98: NA
A99: 4 | B99: WARDROBE | C99: a) Providing & making of wardrobe with cane shutter in 19mm the .Ply 75 mm thk shutter frame to be treated with approved mm thk HDHMR finished in app shade of pu & white laminate from inside. (basic cost of laminate upto 1500 - sheet). With all necessary hardware like lock.handle hinge.etc. &(cost will vary as per design) | D99: 7 | E99: 9 | F99: 1 | G99: =F99*E99*D99 -> 63 | H99: sq.ft | I99: 1800 | J99: =G99*I99 -> ₹ 113,400.00
A100: 5 | B100: SIDE TABLE (WITH DRAWERS) | C100: a) Table of . plywood | D100: 1 | E100: 1.6 | F100: 2 | G100: 2 | H100: no.s | I100: 3500 | J100: =G100*I100 -> ₹ 7,000.00
A101: 6 | B101: STUDY TABLE WITH ONLY 2 DRAWERS | C101: a) Table with . plywood | D101: 4 | E101: 2.6 | F101: 1 | G101: =F101*E101*D101 -> 10.4 | H101: sq.ft | I101: 1800 | J101: =G101*I101 -> ₹ 18,720.00
A102: 7 | B102: DRESSING TABLE WITH MIROR STORAGE | C102: b) Exotic Teak Finish made of premium . plywood | D102: 7 | E102: 3 | F102: 1 | G102: =F102*E102*D102 -> 21 | H102: sq.ft | I102: 1800 | J102: =G102*I102 -> ₹ 37,800.00
A103: 8 | B103: STORAGE ABOVE STUDY | C103: a) Providing & making of o.h storage - above desk in 19mm th . Ply treated with approved laminate from outside finished in approved shade of color lamination & white laminate from inside (basic cost of laminate upto Rs.2500 - sheet.)(basic cost of laminat upto 1500/-sheet). With all necessary hardware like lock, handle hinge.etc. (cost will vary as per design) | D103: 2 | E103: 4 | F103: 1 | G103: =F103*E103*D103 -> 8 | H103: sq.ft | I103: 1800 | J103: =G103*I103 -> ₹ 14,400.00
A105: TOTAL OF THIRD BEDROOM | J105: =SUM(J96:J103) -> ₹ 272,440.00
A107: TOTAL OF FURNITURE WORK (All the above items from Sr. No. A to J) | J107: =J105+J92+J83+J68+J49+J34+J26+J13 -> ₹ 1,307,020.00
A109: A | B109: FALSE CEILING WORK
A111: 1 | B111: FALSE CEILING (GYPSUM) | C111: FIRST BEDROOM | D111: 11 | E111: 11.5 | F111: 1 | G111: =D111*E111*F111 -> 126.5 | H111: sq.ft | I111: 80 | J111: =G111*I111 -> ₹ 10,120.00
C112: KIDS BEDROOM | D112: 11 | E112: 11.5 | F112: 1 | G112: =D112*E112*F112 -> 126.5 | H112: sq.ft | I112: 80 | J112: =G112*I112 -> ₹ 10,120.00
C113: MASTER BEDROOM | D113: 11 | E113: 12 | F113: 1 | G113: =D113*E113*F113 -> 132 | H113: sq.ft | I113: 80 | J113: =G113*I113 -> ₹ 10,560.00
C114: LIVING ROOM | D114: 17.5 | E114: 14.5 | F114: 1 | G114: =D114*E114*F114 -> 253.75 | H114: sq.ft | I114: 80 | J114: =G114*I114 -> ₹ 20,300.00
C115: DINING AREA | D115: 12.3 | E115: 5 | F115: 1 | G115: =D115*E115*F115 -> 61.5 | H115: sq.ft | I115: 80 | J115: =G115*I115 -> ₹ 4,920.00
C116: KITCHEN | D116: 9 | E116: 9.3 | F116: 1 | G116: =D116*E116*F116 -> 83.7 | H116: sq.ft | I116: 80 | J116: =G116*I116 -> ₹ 6,696.00
C117: LOBBY | D117: 5 | E117: 4 | F117: 1 | G117: =D117*E117*F117 -> 20 | H117: sq.ft | I117: 80 | J117: =G117*I117 -> ₹ 1,600.00
C118: PASSAGE | D118: 4 | E118: 6 | F118: 1 | G118: =D118*E118*F118 -> 24 | H118: sq.ft | I118: 80 | J118: =G118*I118 -> ₹ 1,920.00
A119: 2 | B119: FALSE CEILING (ACRELIC/PVC) | C119: BALCONY | D119: 6 | E119: 14 | F119: 1 | G119: =D119*E119*F119 -> 84 | H119: sq.ft | I119: 250 | J119: NA
C120: BALCONY | D120: 3 | E120: 14 | F120: 1 | G120: =D120*E120*F120 -> 42 | H120: sq.ft | I120: 250 | J120: NA
C121: ALL BATHROOMS | D121: 8 | E121: 4 | F121: 3 | G121: =D121*E121*F121 -> 96 | H121: sq.ft | I121: 200 | J121: NA
A122: 3 | B122: WOODEN ELEMENTS | C122: BORDERS | D122: 1 | E122: 8 | F122: 8 | G122: =D122*E122*F122 -> 64 | H122: sq.ft | I122: 200 | J122: NA
A123: 3 | B123: VERTICAL CEILING | C123: COVE CEILING | D123: 1 | E123: =SUM(E111:E118) -> 73.8 | F123: 1 | G123: =D123*E123*F123 -> 73.8 | H123: sq.ft | I123: 90 | J123: =G123*I123 -> ₹ 6,642.00
A124: 4 | B124: GALA CUTTING | C124: LIGHT CUTTING | D124: 1 | E124: 50 | F124: 1 | G124: =D124*E124*F124 -> 50 | H124: sq.ft | I124: 90 | J124: =G124*I124 -> ₹ 4,500.00
A126: TOTAL OF FALSE CEILING WORK | J126: =SUM(J110:J124) -> ₹ 77,378.00
...

Sheet INTERIOR FEES
A1: NESTURA DESIGNS (formerly SA INTERIOR SCAPES)
A2: DETAILED ESTIMATE
A3: S.NO | B3: ITEM | C3: PROPOSED DETAILS/MATERIALS | D3: UNITS | E3: GRAND TOTAL
A6: Interior Designer Fees
A7: Scope of Work: To provide 2d, 3d to client. To provide working drawings . To go for selection of materials(laminate veneer tiles décor all finishing materials) with client . To do site visits and update client as and when required. To Maintain Best Quality of work. Giving Material orders, making list of it and its procurement. Optimum material use and lesser wastage. Provide Labour Teams; get the work done as per the drawings. Rates and bill checking of material and labour. Interlinking and coordination between agencies for speedy work. To direct and maintain speed of work.
B8: Description | C8: Percentage | D8: TOTAL PROJECT COST | E8: DESIGNER FEES
B9: Designing Charges (2d drawings 3d drawings , working drawings , site visits, selection of each item needed.
A11: TOTAL AMOUNT /- | E11: 225000
B12: Interior design fees to be paid in 4 phases as follows:
A13: Phase | B13: Description | D13: Rate(Rs) | E13: AMOUNT(Rs)
A14: 1 | B14: Advance at signing designing fees | D14: 0.45 | E14: =D14*D18 -> ₹ 101,250.00
A15: 2 | B15: Design phase 1 (AFTER SELECTION) | D15: 0.25 | E15: =D15*D18 -> ₹ 56,250.00
A16: 3 | B16: Design phase 2 ( AFTER START OF PROJECT) | D16: 0.2 | E16: =D16*D18 -> ₹ 45,000.00
A17: 4 | B17: Design phase 3 (AFTER HANDOVER) | D17: 0.1 | E17: =D17*D18 -> ₹ 22,500.00
A18: 5 | B18: Designing Charges (2d drawings 3d drawings , working drawings , site visits, selection of each item needed(PUNE ). | D18: =E11 -> ₹ 225,000.00 | E18: =SUM(E14:E17) -> ₹ 225,000.00
D19: TOTAL AMOUNT ( LUMSUM) | E19: =E18 -> ₹ 225,000.00
A23: FINAL PROJECT COST (TOTAL PROJECT COST + INTERIOR DESIGN FEES) | E23: =D9+E19 -> ₹ 225,000.00

Sheet TERMS AND CONDITIONDS
A1: NESTURA DESIGNS (formerly SA INTERIOR SCAPES)
A2: MATERIAL SPECIFICATIONS AND PAYMENTS T&C
A4: ALL FURNITURE WORK WILL BE DONE IN
A6: 1 | B6: 18mm, 12mm, 6mm ply 8x4 sheet. Sliding door will be in 25mm thick blockboard
A7: 2 | B7: Laminate will be in 1 mm thick (inside-colour , outside-colour laminate)
A8: 3 | B8: Hardware, Nails , screws, Adhesives
A10: BRANDS CONSIDERED
A12: 1 | B12: Ply | C12: Basic furniture structure in high quality alternate grade plywood full face gurjan, ISO,ISI grade (Water resistance)
A13: 2 | B13: Laminate | C13: Royal Touch, Real Touch, Merino equivalent brands
A14: 3 | B14: Laminate Finishes | C14: Wood grain shine, wood grain solid, anti fingerprints, HD Gloss, Super Gloss, Textures, Scratch Resistant, PVC laminate etc
A15: 4 | B15: Glass/Mirror | C15: Plain 6mm
A16: 5 | B16: Sliding Track | C16: EBCO (soft closing) Premium
A17: 6 | B17: Adhesives | C17: Falco fix ultramarine and Falco fix EBS
A18: 7 | B18: Paint | C18: Asian, equivalent (Ceiling- luxury emulsion)
A19: 8 | B19: POP | C19: 6x4 sheets, 12MM thickness, Brand Saint Gobain-Gyproc. Gypsum sheet with aluminium metal frame by Ultra
A20: 9 | B20: Electrical Cables | C20: Polycab standard
A21: 10 | B21: Light Panels | C21: Polycab 12w
A22: 11 | B22: Kitchen Ply | C22: Waterproof, BWP
A23: 12 | B23: Kitchen Hardware | C23: EBCO soft closing hinges, Hydraulic pump, Auto hinges
... A26: 15 | B26: Curtains | C26: D'Decor or FnF
A28: PAYMENT TERMS FOR EXECUTION
A30: 1 | B30: 40% before the structural work start on site, after the finalization of 3D designs
A31: 2 | B31: 30% At the start of the carpentry stage
A32: 3 | B32: 20% At the start of wall painting
A33: 4 | B33: 10%At the start of furnishings( Before site handover (before Sofa And dinning installation)
A35: GENERAL NOTES (T&C)
A37: The above mentioned unit rates are subject to the following conditions.
A38: 1 | B38: The unit rate for any of the above items are considered as per standard of MRg material as per base rate .Any variation in the raw or design or finishing material rates.
A39: 2 | B39: Marine ply used in kitchen & toilet only. rest of all furnitures are to be made from BWR ply
A40: 3 | B40: Every room door & toilet doors has been considered with a pair of mortise hand set. Any variation in the hardware cost shall be settled as per actual purchase
A41: 4 | B41: Every room Storages has been considered with a handle upto Rs. 200/- piece. Any cost shall be settled as per actual purchase cost.
A43: GENERAL NOTES
A44: 1 | B44: The above unit rates are valid for 60 days from the date of the Bill of Quantities (BOQ). These rates are subject to changes based on inflation in material or labor costs.
A45: 2 | B45: The quantities mentioned in the BOQ are for estimation purposes only. The BOQ is subject to deviation during execution due to changes in design and site conditions.
A46: 3 | B46: The electrical costs mentioned are approximate and will be charged based on actual costs incurred during execution.
A47: 4 | B47: BMC and society permissions required for the job will be obtained by the owner. The contractor will not be responsible for obtaining these permissions.
A48: 5 | B48: Final billing will be based on actual quantities executed, and a measurement sheet will be provided, checked, and certified by both parties involved.
A49: 6 | B49: The submitted rates are unit rates, and it is assumed that these rates are agreed upon by the contractor. The amount for each item of work is calculated as per the agreed quantities and rates. These rates will apply for settling bills for any additional work executed.
A50: 7 | B50: The contractor will submit an estimate for any unforeseen costs incurred during the project. Such costs will be executed only after receiving written approval from the client. Additional work will be billed based on market rates and execution details.
A51: 8 | B51: Water and electricity will be provided free of charge by the client.
A52: 9 | B52: Plywood material uplifting will be charged as per actuals, based on the number of floors.
A53: 10 | B53: Electrical fittings, such as hanging and decorative lights, fans, TV cables, Wi-Fi routers, CCTV, etc., are not included in the quotation.
A54: 11 | B54: Electronics, such as air conditioners, chimneys, fridges, TVs, etc., must be provided by the client.
A55: 12 | B55: There will be no refund on the initial payment if the client cancels the deal.
A56: 13 | B56: Please be advised that, while we implement floor protection measures (such as floor guards) during the course of the project, any incidental damage to marble, tiling, or other flooring surfaces will not be the responsibility or liability of IAD. Although we take every precaution to safeguard the flooring, the inherent risks of renovation and construction activities mean that some damage may still occur despite these protective measures.
A59: THANK YOU!
